staruxian/__init__.py
staruxian/main.py
staruxian-1.1.4.dist-info/METADATA
staruxian-1.1.4.dist-info/WHEEL
staruxian-1.1.4.dist-info/entry_points.txt
staruxian-1.1.4.dist-info/top_level.txt
staruxian-1.1.4.dist-info/RECORD
