Metadata-Version: 2.1
Name: staruxian
Version: 1.1.4
Summary: Hello I am cosmoboy
Author: Khurshed Ziyovaddinov
Author-email: mrx555888@gmail.com
